moderne/__init__.py
moderne/app.py
moderne/cli.py
moderne/conf.py
moderne/index.py
moderne/main.py
moderne/settings.py
moderne/templates/__init__.py
moderne/templates/app.py
moderne/templates/index.html
moderne/templates/index.py
moderne/templates/main.py
moderne/templates/moderne.png
moderne/templates/settings.py
moderne-0.0.2.dist-info/METADATA
moderne-0.0.2.dist-info/WHEEL
moderne-0.0.2.dist-info/entry_points.txt
moderne-0.0.2.dist-info/top_level.txt
moderne-0.0.2.dist-info/RECORD
