Metadata-Version: 2.1
Name: moderne
Version: 0.0.2
Summary: Moderne Web Framework
Home-page: https://github.com/coryfitz/moderne
Author: Cory Fitz
Author-email: coryalanfitz@gmail.com
Classifier: Programming Language :: Python :: 3
Classifier: License :: OSI Approved :: MIT License
Classifier: Operating System :: OS Independent
Requires-Python: >=3.6
Requires-Dist: psx-syntax>=0.0.2
Requires-Dist: starlette>=0.41.0
Requires-Dist: uvicorn>=0.32.0
